yw_etl_target_clickhouse/Database.py
yw_etl_target_clickhouse/Database_test.py
yw_etl_target_clickhouse/ReceiveStream.py
yw_etl_target_clickhouse/ReceiveStreamManager.py
yw_etl_target_clickhouse/ReceiveStreamManager_test.py
yw_etl_target_clickhouse/ReceiveStream_test.py
yw_etl_target_clickhouse/WorkingDirectory.py
yw_etl_target_clickhouse/WorkingDirectory_test.py
yw_etl_target_clickhouse/__init__.py
yw_etl_target_clickhouse/logging.conf
yw_etl_target_clickhouse/main.py
yw_etl_target_clickhouse/utils.py
yw_etl_target_clickhouse-0.1.8.dist-info/METADATA
yw_etl_target_clickhouse-0.1.8.dist-info/WHEEL
yw_etl_target_clickhouse-0.1.8.dist-info/entry_points.txt
yw_etl_target_clickhouse-0.1.8.dist-info/top_level.txt
yw_etl_target_clickhouse-0.1.8.dist-info/RECORD
